<?xml version='1.0' encoding='UTF-8'?>
<GateDocument version="3">
<!-- The document's features-->

<GateDocumentFeatures>
<Feature>
  <Name className="java.lang.String">gate.SourceURL</Name>
  <Value className="java.lang.String">file:/Users/ignaciobacierofernandez/Desktop/TFG/NLP/Scrap/b/noticia_94_38.txt</Value>
</Feature>
<Feature>
  <Name className="java.lang.String">MimeType</Name>
  <Value className="java.lang.String">text/plain</Value>
</Feature>
<Feature>
  <Name className="java.lang.String">docNewLineType</Name>
  <Value className="java.lang.String"></Value>
</Feature>
</GateDocumentFeatures>
<!-- The document content area with serialized nodes -->

<TextWithNodes><Node id="0"/>"El resto del envío quedó inmediatamente en pausa y no se ha distribuido", decía un comunicado del <Node id="99"/>Ministerio de Salud<Node id="118"/>. "<Node id="121"/>Ahora<Node id="126"/> se ha decidido no utilizar ninguno de estos <Node id="171"/>productos<Node id="180"/> recibidos".
<Node id="193"/></TextWithNodes>
<!-- The default annotation set -->

<AnnotationSet>
<Annotation Id="1" Type="ORG" StartNode="99" EndNode="118">
</Annotation>
<Annotation Id="2" Type="TIME" StartNode="121" EndNode="126">
</Annotation>
<Annotation Id="3" Type="PRODUCT" StartNode="171" EndNode="180">
</Annotation>
</AnnotationSet>

<!-- Named annotation set -->

<AnnotationSet Name="Original markups">
<Annotation Id="0" Type="paragraph" StartNode="0" EndNode="193">
</Annotation>
</AnnotationSet>

</GateDocument>
