<?xml version='1.0' encoding='UTF-8'?>
<GateDocument version="3">
<!-- The document's features-->

<GateDocumentFeatures>
<Feature>
  <Name className="java.lang.String">gate.SourceURL</Name>
  <Value className="java.lang.String">file:/Users/ignaciobacierofernandez/Desktop/TFG/NLP/Scrap/noticia_29_6.txt</Value>
</Feature>
<Feature>
  <Name className="java.lang.String">MimeType</Name>
  <Value className="java.lang.String">text/plain</Value>
</Feature>
<Feature>
  <Name className="java.lang.String">docNewLineType</Name>
  <Value className="java.lang.String">LF</Value>
</Feature>
</GateDocumentFeatures>
<!-- The document content area with serialized nodes -->

<TextWithNodes><Node id="0"/>Los contratos de suministro garantizarán la seguridad del suministro de la <Node id="75"/>empresa<Node id="82"/> hasta <Node id="89"/>2025<Node id="93"/> y más allá, asegura la fuente. 
<Node id="126"/></TextWithNodes>
<!-- The default annotation set -->

<AnnotationSet>
<Annotation Id="1" Type="ORG" StartNode="75" EndNode="82">
</Annotation>
<Annotation Id="2" Type="DATE" StartNode="89" EndNode="93">
</Annotation>
</AnnotationSet>

<!-- Named annotation set -->

<AnnotationSet Name="Original markups">
<Annotation Id="0" Type="paragraph" StartNode="0" EndNode="126">
</Annotation>
</AnnotationSet>

</GateDocument>
